LICENSE
MANIFEST.in
README.MD
README.md
setup.py
libpythonpronew/__init__.py
libpythonpronew/github_api.py
libpythonpronew.egg-info/PKG-INFO
libpythonpronew.egg-info/SOURCES.txt
libpythonpronew.egg-info/dependency_links.txt
libpythonpronew.egg-info/not-zip-safe
libpythonpronew.egg-info/requires.txt
libpythonpronew.egg-info/top_level.txt